test.py
ex05/input.py
ex05/test.py
ex05-0.0.0.8.dist-info/METADATA
ex05-0.0.0.8.dist-info/WHEEL
ex05-0.0.0.8.dist-info/top_level.txt
ex05-0.0.0.8.dist-info/RECORD
