Metadata-Version: 2.1
Name: ex05
Version: 0.0.0.8
Summary: My First Test Package
Home-page: UNKNOWN
Author: es kang
Author-email: cityfox08@naver.com
License: MIT
Platform: UNKNOWN
Requires-Python: >=3
